{
  "$schema": "https://biomejs.dev/schemas/1.5.3/schema.json",
  "organizeImports": {
    "enabled": true
  },
  "linter": {
    "enabled": true,
    "rules": {
      "recommended": true,
      "correctness": {
        "useExhaustiveDependencies": "off"
      },
      "style": {
        "noNonNullAssertion": "off"
      },
      "suspicious": {
        "noExplicitAny": "off",
        "noArrayIndexKey": "off"
      },
      "a11y": {
        "useKeyWithClickEvents": "off"
      },
      "complexity": {
        "noForEach": "off"
      }
    }
  },
  "formatter": {
    "enabled": true,
    "indentStyle": "space"
  },
  "files": {
    "ignore": [
      "frontend/src/helpers/lodash-is-equal.ts",
      ".cache/",
      ".docz/",
      "public/",
      "src/generated",
      "_schema.json",
      "package.json"
    ]
  }
}
